{
  "id": "1681579",
  "name": "rf-mall图标库",
  "font_family": "iconfont",
  "css_prefix_text": "icon",
  "description": "",
  "glyphs": [
    {
      "icon_id": "8655869",
      "name": "店铺",
      "font_class": "dianpu1",
      "unicode": "e6f3",
      "unicode_decimal": 59123
    },
    {
      "icon_id": "11520918",
      "name": "店铺",
      "font_class": "dianpu2",
      "unicode": "e767",
      "unicode_decimal": 59239
    },
    {
      "icon_id": "11606576",
      "name": "KFCFDC_快捷1",
      "font_class": "kuaijie",
      "unicode": "e723",
      "unicode_decimal": 59171
    },
    {
      "icon_id": "15711151",
      "name": "快捷菜单",
      "font_class": "kuaijiecaidan",
      "unicode": "e6f2",
      "unicode_decimal": 59122
    },
    {
      "icon_id": "1301379",
      "name": "下拉",
      "font_class": "xiala",
      "unicode": "e6ef",
      "unicode_decimal": 59119
    },
    {
      "icon_id": "4437603",
      "name": "下箭头",
      "font_class": "xiajiantou2",
      "unicode": "e6f0",
      "unicode_decimal": 59120
    },
    {
      "icon_id": "8694557",
      "name": "下拉",
      "font_class": "xiala-",
      "unicode": "e6f1",
      "unicode_decimal": 59121
    },
    {
      "icon_id": "1382",
      "name": "定位",
      "font_class": "dingwei2",
      "unicode": "e6ec",
      "unicode_decimal": 59116
    },
    {
      "icon_id": "1148895",
      "name": "定位",
      "font_class": "dingwei3",
      "unicode": "e6ed",
      "unicode_decimal": 59117
    },
    {
      "icon_id": "15684944",
      "name": "地点定位",
      "font_class": "didiandingwei",
      "unicode": "e6ee",
      "unicode_decimal": 59118
    },
    {
      "icon_id": "4175511",
      "name": "下箭头",
      "font_class": "xiajiantou1",
      "unicode": "eb6d",
      "unicode_decimal": 60269
    },
    {
      "icon_id": "6855694",
      "name": "店铺",
      "font_class": "dianpu",
      "unicode": "e6eb",
      "unicode_decimal": 59115
    },
    {
      "icon_id": "3529836",
      "name": "定位",
      "font_class": "dingwei1",
      "unicode": "e761",
      "unicode_decimal": 59233
    },
    {
      "icon_id": "12296962",
      "name": "语言切换",
      "font_class": "yuyanqiehuan",
      "unicode": "e6e7",
      "unicode_decimal": 59111
    },
    {
      "icon_id": "1330571",
      "name": "微博",
      "font_class": "weibo",
      "unicode": "e73d",
      "unicode_decimal": 59197
    },
    {
      "icon_id": "1330577",
      "name": "QQ",
      "font_class": "QQ",
      "unicode": "e73e",
      "unicode_decimal": 59198
    },
    {
      "icon_id": "8574987",
      "name": "支付宝",
      "font_class": "zhifubao",
      "unicode": "e6e8",
      "unicode_decimal": 59112
    },
    {
      "icon_id": "14055582",
      "name": "微信",
      "font_class": "weixin1",
      "unicode": "e6e9",
      "unicode_decimal": 59113
    },
    {
      "icon_id": "15559700",
      "name": "淘宝",
      "font_class": "shejiaotubiao-44",
      "unicode": "e6ea",
      "unicode_decimal": 59114
    },
    {
      "icon_id": "397915",
      "name": "键盘，输入",
      "font_class": "jianpanshuru",
      "unicode": "e6e5",
      "unicode_decimal": 59109
    },
    {
      "icon_id": "9242139",
      "name": "REX:输入条形码_48",
      "font_class": "REXshurutiaoxingma_",
      "unicode": "e6e6",
      "unicode_decimal": 59110
    },
    {
      "icon_id": "559613",
      "name": "消息",
      "font_class": "xiaoxi2",
      "unicode": "e6d4",
      "unicode_decimal": 59092
    },
    {
      "icon_id": "617438",
      "name": "分类",
      "font_class": "fenlei2",
      "unicode": "e6d5",
      "unicode_decimal": 59093
    },
    {
      "icon_id": "1514383",
      "name": "账户 #ffffff & 20px",
      "font_class": "zhanghuffffffpx",
      "unicode": "e6d6",
      "unicode_decimal": 59094
    },
    {
      "icon_id": "1514384",
      "name": "密码 #ffffff & 20px",
      "font_class": "mimaffffffpx",
      "unicode": "e6d7",
      "unicode_decimal": 59095
    },
    {
      "icon_id": "4608920",
      "name": "消息",
      "font_class": "xiaoxi3",
      "unicode": "e6d8",
      "unicode_decimal": 59096
    },
    {
      "icon_id": "4945535",
      "name": "验证码",
      "font_class": "yanzhengma",
      "unicode": "e83f",
      "unicode_decimal": 59455
    },
    {
      "icon_id": "5767566",
      "name": "分类",
      "font_class": "fenlei3",
      "unicode": "e6d9",
      "unicode_decimal": 59097
    },
    {
      "icon_id": "7461693",
      "name": "消息",
      "font_class": "xiaoxi4",
      "unicode": "e6db",
      "unicode_decimal": 59099
    },
    {
      "icon_id": "8328383",
      "name": "消息",
      "font_class": "xiaoxi5",
      "unicode": "e6dc",
      "unicode_decimal": 59100
    },
    {
      "icon_id": "9148582",
      "name": "消息",
      "font_class": "xiaoxi6",
      "unicode": "e6dd",
      "unicode_decimal": 59101
    },
    {
      "icon_id": "10995776",
      "name": "验证码",
      "font_class": "yanzhengma1",
      "unicode": "e6de",
      "unicode_decimal": 59102
    },
    {
      "icon_id": "13769974",
      "name": "消息",
      "font_class": "xiaoxi7",
      "unicode": "e6df",
      "unicode_decimal": 59103
    },
    {
      "icon_id": "13982920",
      "name": "首页",
      "font_class": "shouye2",
      "unicode": "e6e0",
      "unicode_decimal": 59104
    },
    {
      "icon_id": "13982922",
      "name": "我的",
      "font_class": "wode1",
      "unicode": "e6e1",
      "unicode_decimal": 59105
    },
    {
      "icon_id": "13984685",
      "name": "购物车",
      "font_class": "gouwuche3",
      "unicode": "e6e2",
      "unicode_decimal": 59106
    },
    {
      "icon_id": "14055588",
      "name": "消息",
      "font_class": "xiaoxi11",
      "unicode": "e6e4",
      "unicode_decimal": 59108
    },
    {
      "icon_id": "4551252",
      "name": "加号",
      "font_class": "jiahao",
      "unicode": "e6d3",
      "unicode_decimal": 59091
    },
    {
      "icon_id": "625966",
      "name": "31-向下箭头",
      "font_class": "xiangxiajiantou",
      "unicode": "e6d2",
      "unicode_decimal": 59090
    },
    {
      "icon_id": "4933349",
      "name": "结束课堂",
      "font_class": "jieshuketang",
      "unicode": "e73a",
      "unicode_decimal": 59194
    },
    {
      "icon_id": "10715415",
      "name": "定位",
      "font_class": "dingwei",
      "unicode": "e6d1",
      "unicode_decimal": 59089
    },
    {
      "icon_id": "10715423",
      "name": "关闭",
      "font_class": "guanbi",
      "unicode": "e6cd",
      "unicode_decimal": 59085
    },
    {
      "icon_id": "10715434",
      "name": "删除",
      "font_class": "shanchu",
      "unicode": "e6ce",
      "unicode_decimal": 59086
    },
    {
      "icon_id": "10715451",
      "name": "相机",
      "font_class": "xiangji1",
      "unicode": "e6cf",
      "unicode_decimal": 59087
    },
    {
      "icon_id": "10715452",
      "name": "图片",
      "font_class": "tupian",
      "unicode": "e6d0",
      "unicode_decimal": 59088
    },
    {
      "icon_id": "4933451",
      "name": "主页的副本",
      "font_class": "zhuyedefuben",
      "unicode": "e76f",
      "unicode_decimal": 59247
    },
    {
      "icon_id": "4142916",
      "name": "更多",
      "font_class": "gengduo",
      "unicode": "e6c6",
      "unicode_decimal": 59078
    },
    {
      "icon_id": "14917824",
      "name": "实心",
      "font_class": "shixin1",
      "unicode": "e6c5",
      "unicode_decimal": 59077
    },
    {
      "icon_id": "4933342",
      "name": "关注",
      "font_class": "guanzhu",
      "unicode": "e736",
      "unicode_decimal": 59190
    },
    {
      "icon_id": "4933341",
      "name": "购物车",
      "font_class": "gouwuche2",
      "unicode": "e735",
      "unicode_decimal": 59189
    },
    {
      "icon_id": "4933352",
      "name": "客服",
      "font_class": "kefu2",
      "unicode": "e73c",
      "unicode_decimal": 59196
    },
    {
      "icon_id": "14910274",
      "name": "上三角",
      "font_class": "shangsanjiao",
      "unicode": "e6c1",
      "unicode_decimal": 59073
    },
    {
      "icon_id": "14910275",
      "name": "下三角",
      "font_class": "xiasanjiao",
      "unicode": "e6c4",
      "unicode_decimal": 59076
    },
    {
      "icon_id": "14909910",
      "name": "下箭头",
      "font_class": "xiajiantou",
      "unicode": "e6be",
      "unicode_decimal": 59070
    },
    {
      "icon_id": "14909911",
      "name": "上箭头",
      "font_class": "shangjiantou",
      "unicode": "e6c0",
      "unicode_decimal": 59072
    },
    {
      "icon_id": "1496251",
      "name": "苹果",
      "font_class": "pingguo",
      "unicode": "e6c1",
      "unicode_decimal": 59073
    },
    {
      "icon_id": "14891696",
      "name": "直播5",
      "font_class": "zhibo51",
      "unicode": "e6c7",
      "unicode_decimal": 59079
    },
    {
      "icon_id": "14891697",
      "name": "直播2",
      "font_class": "zhibo21",
      "unicode": "e6c8",
      "unicode_decimal": 59080
    },
    {
      "icon_id": "14891698",
      "name": "直播3",
      "font_class": "zhibo31",
      "unicode": "e6ca",
      "unicode_decimal": 59082
    },
    {
      "icon_id": "14891699",
      "name": "直播4",
      "font_class": "zhibo41",
      "unicode": "e6cb",
      "unicode_decimal": 59083
    },
    {
      "icon_id": "14891700",
      "name": "直播1",
      "font_class": "zhibo11",
      "unicode": "e6cc",
      "unicode_decimal": 59084
    },
    {
      "icon_id": "8798014",
      "name": "直播",
      "font_class": "zhibo",
      "unicode": "e7d5",
      "unicode_decimal": 59349
    },
    {
      "icon_id": "14843170",
      "name": "关闭",
      "font_class": "guanbi1",
      "unicode": "e6bd",
      "unicode_decimal": 59069
    },
    {
      "icon_id": "14828951",
      "name": "代理商",
      "font_class": "dailishang",
      "unicode": "e6ac",
      "unicode_decimal": 59052
    },
    {
      "icon_id": "14828952",
      "name": "个人信息",
      "font_class": "gerenxinxi",
      "unicode": "e6af",
      "unicode_decimal": 59055
    },
    {
      "icon_id": "14828953",
      "name": "二维码",
      "font_class": "erweima",
      "unicode": "e6b0",
      "unicode_decimal": 59056
    },
    {
      "icon_id": "14828954",
      "name": "区域代理",
      "font_class": "quyudaili",
      "unicode": "e6b1",
      "unicode_decimal": 59057
    },
    {
      "icon_id": "14828955",
      "name": "提现记录",
      "font_class": "tixianjilu",
      "unicode": "e6b2",
      "unicode_decimal": 59058
    },
    {
      "icon_id": "14828956",
      "name": "进行中的佣金",
      "font_class": "jinhangzhongdeyongjin",
      "unicode": "e6b3",
      "unicode_decimal": 59059
    },
    {
      "icon_id": "14828957",
      "name": "我的",
      "font_class": "wode",
      "unicode": "e6b4",
      "unicode_decimal": 59060
    },
    {
      "icon_id": "14828958",
      "name": "团队订单",
      "font_class": "tuanduidingdan",
      "unicode": "e6b5",
      "unicode_decimal": 59061
    },
    {
      "icon_id": "14828959",
      "name": "佣金",
      "font_class": "yongjin1",
      "unicode": "e6b6",
      "unicode_decimal": 59062
    },
    {
      "icon_id": "14828960",
      "name": "我的团队",
      "font_class": "wodetuandui",
      "unicode": "e6b7",
      "unicode_decimal": 59063
    },
    {
      "icon_id": "14828961",
      "name": "我要提现",
      "font_class": "woyaotixian",
      "unicode": "e6b8",
      "unicode_decimal": 59064
    },
    {
      "icon_id": "14828962",
      "name": "自推订单",
      "font_class": "zituidingdan",
      "unicode": "e6ba",
      "unicode_decimal": 59066
    },
    {
      "icon_id": "14828963",
      "name": "我的佣金",
      "font_class": "wodeyongjin",
      "unicode": "e6bb",
      "unicode_decimal": 59067
    },
    {
      "icon_id": "14828964",
      "name": "提现账号",
      "font_class": "tixianzhanghao",
      "unicode": "e6bc",
      "unicode_decimal": 59068
    },
    {
      "icon_id": "13773786",
      "name": "企业",
      "font_class": "shangjia",
      "unicode": "e6ae",
      "unicode_decimal": 59054
    },
    {
      "icon_id": "14784871",
      "name": "空心",
      "font_class": "kongxin",
      "unicode": "e6aa",
      "unicode_decimal": 59050
    },
    {
      "icon_id": "14784872",
      "name": "实心",
      "font_class": "shixin",
      "unicode": "e6ab",
      "unicode_decimal": 59051
    },
    {
      "icon_id": "8035031",
      "name": "首页-01",
      "font_class": "shouye-",
      "unicode": "e69b",
      "unicode_decimal": 59035
    },
    {
      "icon_id": "8035073",
      "name": "分类-01",
      "font_class": "fenlei-",
      "unicode": "e69d",
      "unicode_decimal": 59037
    },
    {
      "icon_id": "8035092",
      "name": "购物车-01",
      "font_class": "gouwuche-",
      "unicode": "e69e",
      "unicode_decimal": 59038
    },
    {
      "icon_id": "8035104",
      "name": "我的-01",
      "font_class": "wode-",
      "unicode": "e6a1",
      "unicode_decimal": 59041
    },
    {
      "icon_id": "8035923",
      "name": "消息-01",
      "font_class": "xiaoxi-",
      "unicode": "e6a4",
      "unicode_decimal": 59044
    },
    {
      "icon_id": "5849183",
      "name": "分销中心",
      "font_class": "fenxiaozhongxin",
      "unicode": "e697",
      "unicode_decimal": 59031
    },
    {
      "icon_id": "12752181",
      "name": "购物车",
      "font_class": "gouwuche_huaban",
      "unicode": "e694",
      "unicode_decimal": 59028
    },
    {
      "icon_id": "858563",
      "name": "推广赚钱",
      "font_class": "tuiguangzhuanqian",
      "unicode": "e680",
      "unicode_decimal": 59008
    },
    {
      "icon_id": "2678604",
      "name": "公告",
      "font_class": "gonggao",
      "unicode": "e67f",
      "unicode_decimal": 59007
    },
    {
      "icon_id": "1276831",
      "name": "消息",
      "font_class": "xiaoxi1",
      "unicode": "e67a",
      "unicode_decimal": 59002
    },
    {
      "icon_id": "1312013",
      "name": "钻石",
      "font_class": "zuanshi",
      "unicode": "e678",
      "unicode_decimal": 59000
    },
    {
      "icon_id": "1504917",
      "name": "设置",
      "font_class": "shezhi4",
      "unicode": "e67c",
      "unicode_decimal": 59004
    },
    {
      "icon_id": "2225235",
      "name": "服务",
      "font_class": "fuwu",
      "unicode": "e67d",
      "unicode_decimal": 59005
    },
    {
      "icon_id": "5206117",
      "name": "订单",
      "font_class": "icon1",
      "unicode": "e67e",
      "unicode_decimal": 59006
    },
    {
      "icon_id": "9626914",
      "name": "钱包",
      "font_class": "qianbao",
      "unicode": "e878",
      "unicode_decimal": 59512
    },
    {
      "icon_id": "9626997",
      "name": "足迹",
      "font_class": "zuji",
      "unicode": "e88e",
      "unicode_decimal": 59534
    },
    {
      "icon_id": "1217795",
      "name": "热门",
      "font_class": "remen3",
      "unicode": "e677",
      "unicode_decimal": 58999
    },
    {
      "icon_id": "3401731",
      "name": "热门",
      "font_class": "remen",
      "unicode": "e6a8",
      "unicode_decimal": 59048
    },
    {
      "icon_id": "14673103",
      "name": "猜你喜欢",
      "font_class": "cainixihuan",
      "unicode": "e682",
      "unicode_decimal": 59010
    },
    {
      "icon_id": "14673104",
      "name": "新品",
      "font_class": "xinpin",
      "unicode": "e686",
      "unicode_decimal": 59014
    },
    {
      "icon_id": "14673105",
      "name": "新品2",
      "font_class": "xinpin2",
      "unicode": "e687",
      "unicode_decimal": 59015
    },
    {
      "icon_id": "14673107",
      "name": "热门",
      "font_class": "remen1",
      "unicode": "e689",
      "unicode_decimal": 59017
    },
    {
      "icon_id": "14673108",
      "name": "推荐",
      "font_class": "tuijian3",
      "unicode": "e68c",
      "unicode_decimal": 59020
    },
    {
      "icon_id": "14673113",
      "name": "猜你喜欢2",
      "font_class": "cainixihuan2",
      "unicode": "e68d",
      "unicode_decimal": 59021
    },
    {
      "icon_id": "14673115",
      "name": "热门2",
      "font_class": "remen2",
      "unicode": "e690",
      "unicode_decimal": 59024
    },
    {
      "icon_id": "14673120",
      "name": "RF",
      "font_class": "tuijian21",
      "unicode": "e691",
      "unicode_decimal": 59025
    },
    {
      "icon_id": "9666185",
      "name": "客服",
      "font_class": "kefu1",
      "unicode": "e673",
      "unicode_decimal": 58995
    },
    {
      "icon_id": "9666187",
      "name": "收藏",
      "font_class": "shoucang4",
      "unicode": "e675",
      "unicode_decimal": 58997
    },
    {
      "icon_id": "9666188",
      "name": "购物车",
      "font_class": "gouwuche1",
      "unicode": "e676",
      "unicode_decimal": 58998
    },
    {
      "icon_id": "4811749",
      "name": "售后客服",
      "font_class": "shouhoukefu",
      "unicode": "e670",
      "unicode_decimal": 58992
    },
    {
      "icon_id": "11778708",
      "name": "顶部",
      "font_class": "dingbu",
      "unicode": "e672",
      "unicode_decimal": 58994
    },
    {
      "icon_id": "376395",
      "name": "已读",
      "font_class": "read",
      "unicode": "e66f",
      "unicode_decimal": 58991
    },
    {
      "icon_id": "126027",
      "name": "gouxuan",
      "font_class": "gouxuan",
      "unicode": "e667",
      "unicode_decimal": 58983
    },
    {
      "icon_id": "797300",
      "name": "分类",
      "font_class": "fenlei",
      "unicode": "e669",
      "unicode_decimal": 58985
    },
    {
      "icon_id": "8675889",
      "name": "列表切换",
      "font_class": "liebiaoqiehuan",
      "unicode": "e66c",
      "unicode_decimal": 58988
    },
    {
      "icon_id": "338290",
      "name": "设置",
      "font_class": "shezhi3",
      "unicode": "e658",
      "unicode_decimal": 58968
    },
    {
      "icon_id": "339563",
      "name": "房源推广",
      "font_class": "icon",
      "unicode": "e659",
      "unicode_decimal": 58969
    },
    {
      "icon_id": "738237",
      "name": "收藏",
      "font_class": "shoucang3",
      "unicode": "e65b",
      "unicode_decimal": 58971
    },
    {
      "icon_id": "1137823",
      "name": "账户余额",
      "font_class": "zhanghuyue",
      "unicode": "e6a7",
      "unicode_decimal": 59047
    },
    {
      "icon_id": "1288647",
      "name": "地址",
      "font_class": "dizhi1",
      "unicode": "e65d",
      "unicode_decimal": 58973
    },
    {
      "icon_id": "1646226",
      "name": "分享",
      "font_class": "fenxiang",
      "unicode": "e660",
      "unicode_decimal": 58976
    },
    {
      "icon_id": "3098815",
      "name": "服务管理",
      "font_class": "fuwuguanli",
      "unicode": "e695",
      "unicode_decimal": 59029
    },
    {
      "icon_id": "3849987",
      "name": "拼团订单",
      "font_class": "pintuandingdan",
      "unicode": "e662",
      "unicode_decimal": 58978
    },
    {
      "icon_id": "4733752",
      "name": "优惠券",
      "font_class": "youhuiquan-copy",
      "unicode": "e663",
      "unicode_decimal": 58979
    },
    {
      "icon_id": "8875701",
      "name": "全部订单",
      "font_class": "quanbudingdan",
      "unicode": "e668",
      "unicode_decimal": 58984
    },
    {
      "icon_id": "11121512",
      "name": "密码重置",
      "font_class": "mimazhongzhi",
      "unicode": "e665",
      "unicode_decimal": 58981
    },
    {
      "icon_id": "11261633",
      "name": "历史记录",
      "font_class": "bianzu",
      "unicode": "e666",
      "unicode_decimal": 58982
    },
    {
      "icon_id": "11520926",
      "name": "砍价",
      "font_class": "kanjia1",
      "unicode": "e76b",
      "unicode_decimal": 59243
    },
    {
      "icon_id": "5327655",
      "name": "历史记录",
      "font_class": "lishijilu1",
      "unicode": "e743",
      "unicode_decimal": 59203
    },
    {
      "icon_id": "5712928",
      "name": "优惠券",
      "font_class": "youhuiquan",
      "unicode": "e652",
      "unicode_decimal": 58962
    },
    {
      "icon_id": "10268392",
      "name": "服务2_选中",
      "font_class": "fuwu_xuanzhong",
      "unicode": "e661",
      "unicode_decimal": 58977
    },
    {
      "icon_id": "10691039",
      "name": "拼团",
      "font_class": "pintuan",
      "unicode": "e653",
      "unicode_decimal": 58963
    },
    {
      "icon_id": "12733323",
      "name": "设置",
      "font_class": "shezhi2",
      "unicode": "e657",
      "unicode_decimal": 58967
    },
    {
      "icon_id": "13972487",
      "name": "服务区域",
      "font_class": "fuwuquyu",
      "unicode": "e685",
      "unicode_decimal": 59013
    },
    {
      "icon_id": "1185",
      "name": "淘宝客推广",
      "font_class": "taobaoketuiguang",
      "unicode": "e649",
      "unicode_decimal": 58953
    },
    {
      "icon_id": "300021",
      "name": "分享给好友icon",
      "font_class": "iconfontfenxiangjitianchong",
      "unicode": "e65e",
      "unicode_decimal": 58974
    },
    {
      "icon_id": "552809",
      "name": "收藏",
      "font_class": "shoucang1",
      "unicode": "e64b",
      "unicode_decimal": 58955
    },
    {
      "icon_id": "731493",
      "name": "全部订单",
      "font_class": "moban",
      "unicode": "e64c",
      "unicode_decimal": 58956
    },
    {
      "icon_id": "738197",
      "name": "账户资产",
      "font_class": "zhanghuzichan",
      "unicode": "e64d",
      "unicode_decimal": 58957
    },
    {
      "icon_id": "903804",
      "name": "砍价",
      "font_class": "kanjia",
      "unicode": "e66b",
      "unicode_decimal": 58987
    },
    {
      "icon_id": "3443907",
      "name": "优惠码送券",
      "font_class": "youhuimasongquan",
      "unicode": "e650",
      "unicode_decimal": 58960
    },
    {
      "icon_id": "768745",
      "name": "进行中",
      "font_class": "shouye1",
      "unicode": "e641",
      "unicode_decimal": 58945
    },
    {
      "icon_id": "9874550",
      "name": "KHCFDC_佣金",
      "font_class": "yongjin",
      "unicode": "e6e3",
      "unicode_decimal": 59107
    },
    {
      "icon_id": "9923738",
      "name": "区域管理",
      "font_class": "quyuguanli",
      "unicode": "e644",
      "unicode_decimal": 58948
    },
    {
      "icon_id": "7275218",
      "name": "Sound 2 (Filled)",
      "font_class": "SoundFilled",
      "unicode": "e664",
      "unicode_decimal": 58980
    },
    {
      "icon_id": "2699684",
      "name": "star",
      "font_class": "star",
      "unicode": "e692",
      "unicode_decimal": 59026
    },
    {
      "icon_id": "5238527",
      "name": "组合消费",
      "font_class": "zuheduozhongxiaofeifangshizuhexiaofei",
      "unicode": "e63e",
      "unicode_decimal": 58942
    },
    {
      "icon_id": "6882983",
      "name": "充值记录",
      "font_class": "chongzhijilu",
      "unicode": "e63f",
      "unicode_decimal": 58943
    },
    {
      "icon_id": "10595632",
      "name": "未完成-流程-状态_jurassic",
      "font_class": "jurassic_not-complete",
      "unicode": "e6c3",
      "unicode_decimal": 59075
    },
    {
      "icon_id": "12340077",
      "name": "已完成",
      "font_class": "yiwancheng",
      "unicode": "e63b",
      "unicode_decimal": 58939
    },
    {
      "icon_id": "13412904",
      "name": "断开",
      "font_class": "duankai",
      "unicode": "e63a",
      "unicode_decimal": 58938
    },
    {
      "icon_id": "6364167",
      "name": "二维码",
      "font_class": "ico",
      "unicode": "e647",
      "unicode_decimal": 58951
    },
    {
      "icon_id": "8017484",
      "name": "empty",
      "font_class": "empty",
      "unicode": "e6a6",
      "unicode_decimal": 59046
    },
    {
      "icon_id": "8103418",
      "name": "客服",
      "font_class": "danseshixintubiao-",
      "unicode": "e639",
      "unicode_decimal": 58937
    },
    {
      "icon_id": "9169986",
      "name": "客服",
      "font_class": "kefu",
      "unicode": "e696",
      "unicode_decimal": 59030
    },
    {
      "icon_id": "868583",
      "name": "icon-添加图片",
      "font_class": "icontianjiatupian",
      "unicode": "e634",
      "unicode_decimal": 58932
    },
    {
      "icon_id": "5093354",
      "name": "相机",
      "font_class": "xiangji",
      "unicode": "e635",
      "unicode_decimal": 58933
    },
    {
      "icon_id": "1388132",
      "name": "nodata-search",
      "font_class": "nodata-search",
      "unicode": "e62b",
      "unicode_decimal": 58923
    },
    {
      "icon_id": "11556758",
      "name": "nodata",
      "font_class": "nodata",
      "unicode": "e638",
      "unicode_decimal": 58936
    },
    {
      "icon_id": "1115013",
      "name": "404",
      "font_class": "404",
      "unicode": "e62a",
      "unicode_decimal": 58922
    },
    {
      "icon_id": "1069170",
      "name": "已过期",
      "font_class": "yiguoqi2",
      "unicode": "e642",
      "unicode_decimal": 58946
    },
    {
      "icon_id": "1069171",
      "name": "已使用",
      "font_class": "yishiyong",
      "unicode": "e643",
      "unicode_decimal": 58947
    },
    {
      "icon_id": "918460",
      "name": "share-arrow",
      "font_class": "icon-share",
      "unicode": "e6ad",
      "unicode_decimal": 59053
    },
    {
      "icon_id": "1219104",
      "name": "分期-我-待发货",
      "font_class": "send-goods",
      "unicode": "e6c2",
      "unicode_decimal": 59074
    },
    {
      "icon_id": "1312069",
      "name": "资料管理",
      "font_class": "ziliaoguanli",
      "unicode": "e648",
      "unicode_decimal": 58952
    },
    {
      "icon_id": "1323679",
      "name": "货到付款",
      "font_class": "huodaofukuan",
      "unicode": "e6bf",
      "unicode_decimal": 59071
    },
    {
      "icon_id": "1715053",
      "name": "转账汇款",
      "font_class": "zhuanzhanghuikuan",
      "unicode": "e651",
      "unicode_decimal": 58961
    },
    {
      "icon_id": "2168758",
      "name": "卡",
      "font_class": "qia11",
      "unicode": "e6da",
      "unicode_decimal": 59098
    },
    {
      "icon_id": "2306154",
      "name": "搜索",
      "font_class": "sousuo3",
      "unicode": "e65c",
      "unicode_decimal": 58972
    },
    {
      "icon_id": "4282553",
      "name": "积分卡",
      "font_class": "jifenqia",
      "unicode": "e66d",
      "unicode_decimal": 58989
    },
    {
      "icon_id": "4380286",
      "name": "现金支付",
      "font_class": "cash_payment",
      "unicode": "e66e",
      "unicode_decimal": 58990
    },
    {
      "icon_id": "4656692",
      "name": "商品评价",
      "font_class": "shangpinpingjia",
      "unicode": "e671",
      "unicode_decimal": 58993
    },
    {
      "icon_id": "4867082",
      "name": "密码",
      "font_class": "mima1",
      "unicode": "e674",
      "unicode_decimal": 58996
    },
    {
      "icon_id": "5723780",
      "name": "支票",
      "font_class": "zhipiao",
      "unicode": "e68a",
      "unicode_decimal": 59018
    },
    {
      "icon_id": "5922506",
      "name": "不可查看",
      "font_class": "bukechakan",
      "unicode": "e683",
      "unicode_decimal": 59011
    },
    {
      "icon_id": "5922507",
      "name": "可查看1",
      "font_class": "kechakan",
      "unicode": "e684",
      "unicode_decimal": 59012
    },
    {
      "icon_id": "6246593",
      "name": "待评价",
      "font_class": "icon-test21",
      "unicode": "e68e",
      "unicode_decimal": 59022
    },
    {
      "icon_id": "6334358",
      "name": "搜索",
      "font_class": "sousuo11",
      "unicode": "e693",
      "unicode_decimal": 59027
    },
    {
      "icon_id": "7150084",
      "name": "转账",
      "font_class": "zhuanzhang",
      "unicode": "e698",
      "unicode_decimal": 59032
    },
    {
      "icon_id": "7226221",
      "name": "搜索",
      "font_class": "sousuo2",
      "unicode": "e699",
      "unicode_decimal": 59033
    },
    {
      "icon_id": "7256697",
      "name": "个人资料",
      "font_class": "gerenziliao",
      "unicode": "e69a",
      "unicode_decimal": 59034
    },
    {
      "icon_id": "7900771",
      "name": "售后服务-自动评价",
      "font_class": "shouhoufuwu-zidongpingjia",
      "unicode": "e69c",
      "unicode_decimal": 59036
    },
    {
      "icon_id": "8172166",
      "name": "眼睛 (1)",
      "font_class": "yanjing11",
      "unicode": "e69f",
      "unicode_decimal": 59039
    },
    {
      "icon_id": "8286483",
      "name": "发票管理",
      "font_class": "fapiaoguanli",
      "unicode": "e6a0",
      "unicode_decimal": 59040
    },
    {
      "icon_id": "11519672",
      "name": "日历",
      "font_class": "rili",
      "unicode": "e746",
      "unicode_decimal": 59206
    },
    {
      "icon_id": "12276548",
      "name": "30 --第三方成本应付发票暂估报账单",
      "font_class": "--disanfangchengbenyingfufapiaozangubaozhangdan",
      "unicode": "e6a2",
      "unicode_decimal": 59042
    },
    {
      "icon_id": "13175713",
      "name": "copy",
      "font_class": "copy",
      "unicode": "e6a3",
      "unicode_decimal": 59043
    },
    {
      "icon_id": "13259316",
      "name": "待评价",
      "font_class": "icon-test2-copy",
      "unicode": "e999",
      "unicode_decimal": 59801
    },
    {
      "icon_id": "5888196",
      "name": "咖啡",
      "font_class": "kafei",
      "unicode": "e66a",
      "unicode_decimal": 58986
    },
    {
      "icon_id": "5925271",
      "name": "VIP/至尊",
      "font_class": "iLinkapp-",
      "unicode": "e654",
      "unicode_decimal": 58964
    },
    {
      "icon_id": "6022237",
      "name": "扫描",
      "font_class": "saomiao",
      "unicode": "e60d",
      "unicode_decimal": 58893
    },
    {
      "icon_id": "6062033",
      "name": "设置 (2)",
      "font_class": "shezhi",
      "unicode": "e60f",
      "unicode_decimal": 58895
    },
    {
      "icon_id": "6172059",
      "name": "售后退款",
      "font_class": "shouhoutuikuan",
      "unicode": "e631",
      "unicode_decimal": 58929
    },
    {
      "icon_id": "6253715",
      "name": "购物车",
      "font_class": "gouwuche",
      "unicode": "e609",
      "unicode_decimal": 58889
    },
    {
      "icon_id": "6295405",
      "name": "地址",
      "font_class": "dizhi",
      "unicode": "e614",
      "unicode_decimal": 58900
    },
    {
      "icon_id": "6529895",
      "name": "分类",
      "font_class": "icon-category",
      "unicode": "e706",
      "unicode_decimal": 59142
    },
    {
      "icon_id": "6529908",
      "name": "星星",
      "font_class": "xingxing",
      "unicode": "e70b",
      "unicode_decimal": 59147
    },
    {
      "icon_id": "6693314",
      "name": "团队",
      "font_class": "tuandui",
      "unicode": "e633",
      "unicode_decimal": 58931
    },
    {
      "icon_id": "6834270",
      "name": "左",
      "font_class": "zuo",
      "unicode": "e63c",
      "unicode_decimal": 58940
    },
    {
      "icon_id": "6935740",
      "name": "已过期",
      "font_class": "yiguoqi1",
      "unicode": "e700",
      "unicode_decimal": 59136
    },
    {
      "icon_id": "6966930",
      "name": "收藏",
      "font_class": "shoucang2",
      "unicode": "e62e",
      "unicode_decimal": 58926
    },
    {
      "icon_id": "7055187",
      "name": "积分卡-01",
      "font_class": "jifenqia-",
      "unicode": "e637",
      "unicode_decimal": 58935
    },
    {
      "icon_id": "7090058",
      "name": "收货地址",
      "font_class": "shouhuodizhi",
      "unicode": "e712",
      "unicode_decimal": 59154
    },
    {
      "icon_id": "7090084",
      "name": "已收货",
      "font_class": "yishouhuo",
      "unicode": "e71a",
      "unicode_decimal": 59162
    },
    {
      "icon_id": "7365944",
      "name": "点赞",
      "font_class": "dianzan-ash",
      "unicode": "e617",
      "unicode_decimal": 58903
    },
    {
      "icon_id": "7905577",
      "name": "购物 (1)@2x",
      "font_class": "gouwux",
      "unicode": "e65f",
      "unicode_decimal": 58975
    },
    {
      "icon_id": "8084566",
      "name": "密码",
      "font_class": "mima",
      "unicode": "e627",
      "unicode_decimal": 58919
    },
    {
      "icon_id": "8602964",
      "name": "精选",
      "font_class": "jingxuan",
      "unicode": "e792",
      "unicode_decimal": 59282
    },
    {
      "icon_id": "10693606",
      "name": "邀请",
      "font_class": "yaoqing",
      "unicode": "e629",
      "unicode_decimal": 58921
    },
    {
      "icon_id": "14867",
      "name": "电话",
      "font_class": "dianhua",
      "unicode": "e615",
      "unicode_decimal": 58901
    },
    {
      "icon_id": "584114",
      "name": "删除",
      "font_class": "iconfontshanchu1",
      "unicode": "e619",
      "unicode_decimal": 58905
    },
    {
      "icon_id": "584772",
      "name": "钱包",
      "font_class": "iconfontweixin",
      "unicode": "e611",
      "unicode_decimal": 58897
    },
    {
      "icon_id": "630079",
      "name": "我的优惠券",
      "font_class": "wodeyouhuiquan",
      "unicode": "e65a",
      "unicode_decimal": 58970
    },
    {
      "icon_id": "741265",
      "name": "支付宝",
      "font_class": "alipay",
      "unicode": "e636",
      "unicode_decimal": 58934
    },
    {
      "icon_id": "753448",
      "name": "上",
      "font_class": "shang",
      "unicode": "e624",
      "unicode_decimal": 58916
    },
    {
      "icon_id": "765544",
      "name": "订单",
      "font_class": "shouye",
      "unicode": "e626",
      "unicode_decimal": 58918
    },
    {
      "icon_id": "807373",
      "name": "群组",
      "font_class": "qunzu",
      "unicode": "e625",
      "unicode_decimal": 58917
    },
    {
      "icon_id": "851714",
      "name": "删除 (4)",
      "font_class": "shanchu4",
      "unicode": "e622",
      "unicode_decimal": 58914
    },
    {
      "icon_id": "996868",
      "name": "取消隐藏",
      "font_class": "ai47",
      "unicode": "e6a5",
      "unicode_decimal": 59045
    },
    {
      "icon_id": "1025324",
      "name": "消息",
      "font_class": "xiaoxi",
      "unicode": "e618",
      "unicode_decimal": 58904
    },
    {
      "icon_id": "1025830",
      "name": "箭头",
      "font_class": "jiantour-copy",
      "unicode": "e600",
      "unicode_decimal": 58880
    },
    {
      "icon_id": "1120967",
      "name": "分享",
      "font_class": "fenxiang2",
      "unicode": "e61e",
      "unicode_decimal": 58910
    },
    {
      "icon_id": "1134327",
      "name": "评价",
      "font_class": "pingjia",
      "unicode": "e67b",
      "unicode_decimal": 59003
    },
    {
      "icon_id": "1137794",
      "name": "待付款",
      "font_class": "daifukuan",
      "unicode": "e68f",
      "unicode_decimal": 59023
    },
    {
      "icon_id": "1166359",
      "name": "显示图层",
      "font_class": "yanjing",
      "unicode": "e628",
      "unicode_decimal": 58920
    },
    {
      "icon_id": "1176682",
      "name": "评论",
      "font_class": "pinglun-copy",
      "unicode": "e612",
      "unicode_decimal": 58898
    },
    {
      "icon_id": "1255576",
      "name": "电话",
      "font_class": "dianhua-copy",
      "unicode": "e621",
      "unicode_decimal": 58913
    },
    {
      "icon_id": "1311999",
      "name": "收藏",
      "font_class": "shoucang",
      "unicode": "e645",
      "unicode_decimal": 58949
    },
    {
      "icon_id": "1472519",
      "name": "选中",
      "font_class": "xuanzhong2",
      "unicode": "e62f",
      "unicode_decimal": 58927
    },
    {
      "icon_id": "1472525",
      "name": "购物车_1",
      "font_class": "gouwuche_",
      "unicode": "e630",
      "unicode_decimal": 58928
    },
    {
      "icon_id": "1629870",
      "name": "定位",
      "font_class": "icon-test",
      "unicode": "e60c",
      "unicode_decimal": 58892
    },
    {
      "icon_id": "1629921",
      "name": "星形",
      "font_class": "icon-test1",
      "unicode": "e632",
      "unicode_decimal": 58930
    },
    {
      "icon_id": "1703533",
      "name": "编辑",
      "font_class": "bianji",
      "unicode": "e646",
      "unicode_decimal": 58950
    },
    {
      "icon_id": "1727570",
      "name": "333加载loading-A",
      "font_class": "jiazailoading-A",
      "unicode": "e8fc",
      "unicode_decimal": 59644
    },
    {
      "icon_id": "1837604",
      "name": "左箭头",
      "font_class": "zuoshang",
      "unicode": "e613",
      "unicode_decimal": 58899
    },
    {
      "icon_id": "1892596",
      "name": "卡",
      "font_class": "qia",
      "unicode": "e62c",
      "unicode_decimal": 58924
    },
    {
      "icon_id": "1920285",
      "name": "加",
      "font_class": "jia2",
      "unicode": "e60a",
      "unicode_decimal": 58890
    },
    {
      "icon_id": "2007943",
      "name": "回复",
      "font_class": "huifu",
      "unicode": "e68b",
      "unicode_decimal": 59019
    },
    {
      "icon_id": "2018267",
      "name": "搜索",
      "font_class": "sousuo",
      "unicode": "e7ce",
      "unicode_decimal": 59342
    },
    {
      "icon_id": "2180958",
      "name": "左箭头",
      "font_class": "arrow-fine-up",
      "unicode": "e601",
      "unicode_decimal": 58881
    },
    {
      "icon_id": "2256504",
      "name": "热销",
      "font_class": "hot",
      "unicode": "e60e",
      "unicode_decimal": 58894
    },
    {
      "icon_id": "2377047",
      "name": "历史记录",
      "font_class": "lishijilu",
      "unicode": "e6b9",
      "unicode_decimal": 59065
    },
    {
      "icon_id": "2463879",
      "name": "征信查询-支付宝测评-05",
      "font_class": "zhengxinchaxun-zhifubaoceping-",
      "unicode": "e616",
      "unicode_decimal": 58902
    },
    {
      "icon_id": "2695894",
      "name": "闹钟 (1)",
      "font_class": "naozhong",
      "unicode": "e64a",
      "unicode_decimal": 58954
    },
    {
      "icon_id": "2721140",
      "name": "主页",
      "font_class": "xiatubiao--copy",
      "unicode": "e608",
      "unicode_decimal": 58888
    },
    {
      "icon_id": "2848621",
      "name": "收 藏_选中状态",
      "font_class": "shoucang_xuanzhongzhuangtai",
      "unicode": "e6a9",
      "unicode_decimal": 59049
    },
    {
      "icon_id": "2931271",
      "name": "加",
      "font_class": "jia1",
      "unicode": "e61c",
      "unicode_decimal": 58908
    },
    {
      "icon_id": "3027258",
      "name": "红包",
      "font_class": "hongbao",
      "unicode": "e85b",
      "unicode_decimal": 59483
    },
    {
      "icon_id": "3095027",
      "name": "帮助",
      "font_class": "bangzhu1",
      "unicode": "e63d",
      "unicode_decimal": 58941
    },
    {
      "icon_id": "3174814",
      "name": "左箭头",
      "font_class": "arrow-left-bottom",
      "unicode": "e602",
      "unicode_decimal": 58882
    },
    {
      "icon_id": "3174825",
      "name": "左箭头",
      "font_class": "arrow-right-bottom",
      "unicode": "e603",
      "unicode_decimal": 58883
    },
    {
      "icon_id": "3174832",
      "name": "左箭头",
      "font_class": "arrow-left-top",
      "unicode": "e604",
      "unicode_decimal": 58884
    },
    {
      "icon_id": "3216144",
      "name": "消息",
      "font_class": "icon--",
      "unicode": "e744",
      "unicode_decimal": 59204
    },
    {
      "icon_id": "3446700",
      "name": "账号",
      "font_class": "ef-zhanghao",
      "unicode": "e64e",
      "unicode_decimal": 58958
    },
    {
      "icon_id": "3492772",
      "name": "左箭头",
      "font_class": "zuojiantou-up",
      "unicode": "e605",
      "unicode_decimal": 58885
    },
    {
      "icon_id": "3718987",
      "name": "下",
      "font_class": "xia",
      "unicode": "e62d",
      "unicode_decimal": 58925
    },
    {
      "icon_id": "3946301",
      "name": "020-减号",
      "font_class": "-jianhao",
      "unicode": "e60b",
      "unicode_decimal": 58891
    },
    {
      "icon_id": "3977929",
      "name": "微信支付",
      "font_class": "weixinzhifu",
      "unicode": "e61a",
      "unicode_decimal": 58906
    },
    {
      "icon_id": "4146395",
      "name": "评论",
      "font_class": "comment",
      "unicode": "e64f",
      "unicode_decimal": 58959
    },
    {
      "icon_id": "4625560",
      "name": "微信",
      "font_class": "weixin",
      "unicode": "e61f",
      "unicode_decimal": 58911
    },
    {
      "icon_id": "4640927",
      "name": "分类",
      "font_class": "fenlei1",
      "unicode": "e620",
      "unicode_decimal": 58912
    },
    {
      "icon_id": "4682698",
      "name": "二级页-预存款",
      "font_class": "erjiye-yucunkuan",
      "unicode": "e623",
      "unicode_decimal": 58915
    },
    {
      "icon_id": "4685380",
      "name": "关于",
      "font_class": "guanyu",
      "unicode": "e640",
      "unicode_decimal": 58944
    },
    {
      "icon_id": "4685706",
      "name": "下载",
      "font_class": "Group-",
      "unicode": "e688",
      "unicode_decimal": 59016
    },
    {
      "icon_id": "4920878",
      "name": "右",
      "font_class": "you",
      "unicode": "e606",
      "unicode_decimal": 58886
    },
    {
      "icon_id": "4972352",
      "name": "钱包",
      "font_class": "wallett",
      "unicode": "e6c9",
      "unicode_decimal": 59081
    },
    {
      "icon_id": "5051010",
      "name": "左箭头",
      "font_class": "forward",
      "unicode": "e607",
      "unicode_decimal": 58887
    },
    {
      "icon_id": "5079863",
      "name": "皇冠",
      "font_class": "huangguan",
      "unicode": "e681",
      "unicode_decimal": 59009
    },
    {
      "icon_id": "5081669",
      "name": "推荐",
      "font_class": "tuijian",
      "unicode": "e610",
      "unicode_decimal": 58896
    },
    {
      "icon_id": "5240374",
      "name": "帮助 (1)",
      "font_class": "bangzhu",
      "unicode": "e679",
      "unicode_decimal": 59001
    },
    {
      "icon_id": "5268137",
      "name": "分享",
      "font_class": "share",
      "unicode": "e656",
      "unicode_decimal": 58966
    },
    {
      "icon_id": "5364555",
      "name": "群组",
      "font_class": "qunzu1",
      "unicode": "e655",
      "unicode_decimal": 58965
    },
    {
      "icon_id": "5542611",
      "name": "已过期",
      "font_class": "yiguoqi",
      "unicode": "e997",
      "unicode_decimal": 59799
    },
    {
      "icon_id": "5712918",
      "name": "设置",
      "font_class": "shezhi1",
      "unicode": "e61d",
      "unicode_decimal": 58909
    },
    {
      "icon_id": "5772883",
      "name": "叉号",
      "font_class": "fork",
      "unicode": "e61b",
      "unicode_decimal": 58907
    }
  ]
}
